{
  "$schema": "https://biomejs.dev/schemas/2.4.12/schema.json",
  "vcs": {
    "enabled": true,
    "clientKind": "git",
    "useIgnoreFile": true
  },
  "files": {
    "ignoreUnknown": false
  },
  "overrides": [
    {
      "includes": ["**/*.config.*"],
      "linter": {
        "rules": {
          "style": {
            "noDefaultExport": "off"
          }
        }
      }
    }
  ],
  "formatter": {
    "enabled": true,
    "indentStyle": "space"
  },
  "linter": {
    "enabled": true,
    "rules": {
      "recommended": true,
      "correctness": {
        "useImportExtensions": "on"
      },
      "style": {
        "noDefaultExport": "error",
        "noRestrictedImports": {
          "level": "error",
          "options": {
            "patterns": [
              {
                "group": ["../**/*"],
                "message": "Avoid relative imports deeper than one level. Use `@/` absolute paths instead."
              }
            ]
          }
        },
        "useFilenamingConvention": {
          "level": "error",
          "options": {
            "filenameCases": ["export", "kebab-case"]
          }
        },
        "useNamingConvention": "on"
      }
    }
  },
  "html": {
    "experimentalFullSupportEnabled": true,
    "formatter": {
      "enabled": true
    }
  },
  "css": {
    "formatter": {
      "quoteStyle": "single"
    }
  },
  "javascript": {
    "formatter": {
      "quoteStyle": "single"
    }
  },
  "assist": {
    "enabled": true,
    "actions": {
      "source": {
        "organizeImports": "on",
        "useSortedProperties": "on"
      }
    }
  }
}
